oozie/__init__.py
oozie/httputil2.py
oozie/httputil3.py
oozie/oozie.py
oozie_api-1.2.0.dist-info/LICENSE
oozie_api-1.2.0.dist-info/METADATA
oozie_api-1.2.0.dist-info/WHEEL
oozie_api-1.2.0.dist-info/top_level.txt
oozie_api-1.2.0.dist-info/RECORD
