Metadata-Version: 2.1
Name: oozie-api
Version: 1.2.0
Summary: Python wrapper for Oozie Webservice REST API. Forked from oozie-webservice-api.
Home-page: https://github.com/zsaltys/oozie-webservice-api
Author: z1lv1n4s
Author-email: zilvinas.saltys@gmail.com
License: MIT
Download-URL: https://github.com/zsaltys/oozie-webservice-api/archive/master.zip
Keywords: oozie,webservice,api
Platform: UNKNOWN
Classifier: Programming Language :: Python :: 2
Classifier: Programming Language :: Python :: 3
Classifier: License :: OSI Approved :: MIT License
Classifier: Operating System :: OS Independent
Requires-Python: >=2.6
License-File: LICENSE
